LICENSE
MANIFEST.in
README.md
setup.py
libs/open_jtalk/src/CMakeLists.txt
libs/open_jtalk/src/COPYING
libs/open_jtalk/src/README
libs/open_jtalk/src/bin/open_jtalk.c
libs/open_jtalk/src/mecab2njd/mecab2njd.c
libs/open_jtalk/src/mecab2njd/mecab2njd.h
libs/open_jtalk/src/njd/njd.c
libs/open_jtalk/src/njd/njd.h
libs/open_jtalk/src/njd/njd_node.c
libs/open_jtalk/src/njd_set_accent_phrase/njd_set_accent_phrase.c
libs/open_jtalk/src/njd_set_accent_phrase/njd_set_accent_phrase.h
libs/open_jtalk/src/njd_set_accent_phrase/njd_set_accent_phrase_rule_utf_8.h
libs/open_jtalk/src/njd_set_accent_type/njd_set_accent_type.c
libs/open_jtalk/src/njd_set_accent_type/njd_set_accent_type.h
libs/open_jtalk/src/njd_set_accent_type/njd_set_accent_type_rule_utf_8.h
libs/open_jtalk/src/njd_set_digit/njd_set_digit.c
libs/open_jtalk/src/njd_set_digit/njd_set_digit.h
libs/open_jtalk/src/njd_set_digit/njd_set_digit_rule_utf_8.h
libs/open_jtalk/src/njd_set_long_vowel/njd_set_long_vowel.c
libs/open_jtalk/src/njd_set_long_vowel/njd_set_long_vowel.h
libs/open_jtalk/src/njd_set_long_vowel/njd_set_long_vowel_rule_utf_8.h
libs/open_jtalk/src/njd_set_pronunciation/njd_set_pronunciation.c
libs/open_jtalk/src/njd_set_pronunciation/njd_set_pronunciation.h
libs/open_jtalk/src/njd_set_pronunciation/njd_set_pronunciation_rule_utf_8.h
libs/open_jtalk/src/njd_set_unvoiced_vowel/njd_set_unvoiced_vowel.c
libs/open_jtalk/src/njd_set_unvoiced_vowel/njd_set_unvoiced_vowel.h
libs/open_jtalk/src/njd_set_unvoiced_vowel/njd_set_unvoiced_vowel_rule_utf_8.h
libs/open_jtalk/src/text2mecab/text2mecab.c
libs/open_jtalk/src/text2mecab/text2mecab.h
libs/open_jtalk/src/text2mecab/text2mecab_rule_ascii_for_euc_jp.h
libs/open_jtalk/src/text2mecab/text2mecab_rule_ascii_for_shift_jis.h
libs/open_jtalk/src/text2mecab/text2mecab_rule_ascii_for_utf_8.h
libs/open_jtalk/src/text2mecab/text2mecab_rule_euc_jp.h
libs/open_jtalk/src/text2mecab/text2mecab_rule_shift_jis.h
libs/open_jtalk/src/text2mecab/text2mecab_rule_utf_8.h
natsume.egg-info/PKG-INFO
natsume.egg-info/SOURCES.txt
natsume.egg-info/dependency_links.txt
natsume.egg-info/entry_points.txt
natsume.egg-info/requires.txt
natsume.egg-info/top_level.txt
