Metadata-Version: 2.1
Name: natsume
Version: 1.1.2
Summary: A Japanese text frontend processing toolkit
Home-page: https://github.com/faruzan0820/natsume
Author: faruzan0820
Author-email: faruzankawaii@outlook.com
License: Apache 2.0
License-File: LICENSE
